fc_xd_bigdata.py
fc_aj-2.0.dist-info/METADATA
fc_aj-2.0.dist-info/WHEEL
fc_aj-2.0.dist-info/top_level.txt
fc_aj-2.0.dist-info/RECORD
