Metadata-Version: 2.1
Name: fc-aj
Version: 2.0
Summary: 余光都是你
Home-page: UNKNOWN
Author: 啊佳
Author-email: 2441463947@qq.com
License: UNKNOWN
Platform: UNKNOWN
